Metadata-Version: 2.1
Name: torch-efficient-distloss
Version: 0.1.3
Summary: Efficient distortion loss with O(n) realization.
Home-page: https://github.com/sunset1995
Author: Cheng Sun
Author-email: chengsun@gapp.nthu.edu.tw
License: MIT
License-File: LICENSE
